{
    "name": "Web Track Environment",
    "values": [
        {
            "key": "base_url",
            "value": "http://127.0.0.1:8000/api",
            "type": "default",
            "enabled": true
        },
        {
            "key": "email",
            "value": "admin@example.com",
            "type": "default",
            "enabled": true
        },
        {
            "key": "password",
            "value": "password",
            "type": "default",
            "enabled": true
        },
        {
            "key": "csrf_token",
            "value": "",
            "type": "default",
            "enabled": true
        }
    ],
    "_postman_variable_scope": "environment"
}